methoddispatch/__init__.py
methoddispatch/_methoddispatch.py
methoddispatch/methoddispatch2.py
methoddispatch/methoddispatch3.py
methoddispatch/methoddispatch36.py
methoddispatch-5.0.1.dist-info/LICENSE.txt
methoddispatch-5.0.1.dist-info/METADATA
methoddispatch-5.0.1.dist-info/WHEEL
methoddispatch-5.0.1.dist-info/top_level.txt
methoddispatch-5.0.1.dist-info/RECORD
