Metadata-Version: 2.1
Name: methoddispatch
Version: 5.0.1
Summary: singledispatch decorator for class methods.
Home-page: https://github.com/seequent/methoddispatch
Author: Seequent Ltd
Author-email: tim.mitchell@seequent.com
License: BSD
Keywords: single dispatch decorator method
Platform: UNKNOWN
Classifier: Programming Language :: Python
Classifier: Programming Language :: Python :: 3.8
Classifier: Programming Language :: Python :: 3.9
Classifier: Programming Language :: Python :: 3.10
Classifier: Programming Language :: Python :: 3.11
Classifier: License :: OSI Approved :: BSD License
License-File: LICENSE.txt
